{"originContentModify": "<p>\u6740\u4eba\u72af\u2193\u2193\u2193</p><p><br></p><p>\u6279\u6ce8\uff1a\u2191\u4f60\u8bf4\u7684\u592a\u591a\u4e86</p><p>\uff08\u8bf7\u52ff\u53d1\u5e03\u5267\u900f\u5185\u5bb9\uff0c\u5f71\u54cd\u4ed6\u4eba\u89c2\u611f\uff09</p>", "uid": 36207194, "commentSum": 82, "reasonType": 10, "punishTitle": "\u5728\u5f39\u5e55\u4e2d\u53d1\u5e03\u5267\u900f\u4fe1\u606f", "punishTime": 1499914519000, "blockedType": 0, "moralNum": 20, "reasonTypeName": "\u53d1\u5e03\u5267\u900f\u4fe1\u606f", "punishType": 2, "blockedDays": 7, "id": 40358, "originType": 2, "face": "http://i0.hdslb.com/bfs/face/48be3df820711d1e949371897ee619b343ecbf1a.jpg", "blockedForever": false, "uname": "Smallsnowpanda"}