{"punishType": 2, "reasonType": 9, "face": "http://i2.hdslb.com/bfs/face/f4188fb0998cea5c3506ae5ec23bff32b3a74add.jpg", "punishTitle": "\u5728\u8bc4\u8bba\u4e2d\u53d1\u5e03\u5f15\u6218\u8a00\u8bba", "id": 28730, "originType": 1, "blockedDays": 3, "blockedType": 0, "moralNum": 0, "uid": 13596275, "blockedForever": false, "originContentModify": "\u7cbe\u795e\u5236\u88c1\uff0c\u5927 \u65e5\u672c\u5e1d\u56fd\u4e07\u5c81\u5927\u4e1c\u4e9a\u5171\u8363\u5708\u4e07\u5c81", "reasonTypeName": "\u53d1\u5e03\u5f15\u6218\u8a00\u8bba", "uname": "\u6211\u5927b\u7ad9\u9038\u7edf\u4e8c\u6b21\u5143", "commentSum": 269, "punishTime": 1496170939000}