{"id": 2165, "uid": 22715354, "uname": "\u4e00\u5149\u5e74\u7684\u8ddd\u79bb\u6709\u591a\u8fdc\u00b7", "face": "http://i2.hdslb.com/bfs/face/8a8aa3ff6973304f7c7ffafd6f1857204b8a5288.jpg", "originContentModify": "\u56de\u590d @\u54bd\u4e86\u4e2a\u553e\u6cab:\u4f60\u6bcd\u4eb2\u90a3\u4e2a**\u751f\u51fa\u4f60\u8fd9\u4e48**\u5bf9\u4e16\u754c\u90fd\u662f\u7f6a\u5b7d\uff01\u8ba9\u6211\u4e00\u811a\u628a\u4f60\u8e22\u6b7b\u4e3a\u6c11\u9664\u5bb3\u3002", "originType": 1, "reasonType": 7, "punishTime": 1488899124000, "punishType": 2, "moralNum": 0, "blockedDays": 3, "blockedForever": false, "commentSum": 65, "punishTitle": "\u5728\u8bc4\u8bba\u4e2d\u53d1\u5e03\u4eba\u8eab\u653b\u51fb\u8a00\u8bba", "reasonTypeName": "\u53d1\u5e03\u4eba\u8eab\u653b\u51fb\u8a00\u8bba"}