{"punishTime": 1500620646000, "uid": 31706607, "blockedType": 0, "moralNum": 20, "blockedForever": false, "face": "http://i0.hdslb.com/bfs/face/b1a855e679ac0e41d519d506f772b882849c94ee.jpg", "reasonTypeName": "\u53d1\u5e03\u5267\u900f\u4fe1\u606f", "blockedDays": 7, "uname": "\u5a77\u5b50_\u4f26\u56de\u4e0d\u53d8", "commentSum": 88, "originType": 2, "punishType": 2, "originContentModify": "<p>**\u9884\u8a00\u5bb6\uff0c*\u5973\u5deb\uff0c*\u5b88\u536b\uff0c*\u730e\u4eba</p><p><br></p><p>\u6279\u6ce8\uff1a\u53ef\u4ee5\u51d1\u4e00\u684c\u72fc\u4eba\u6740\u4e86</p><p>\uff08\u8bf7\u52ff\u5728\u89c6\u9891\u5185\u53d1\u5e03\u5267\u900f\u5185\u5bb9\uff09</p>", "punishTitle": "\u5728\u5f39\u5e55\u4e2d\u53d1\u5e03\u5267\u900f\u4fe1\u606f", "reasonType": 10, "id": 44771}