{"punishType": 2, "reasonType": 7, "face": "http://i0.hdslb.com/bfs/face/fa34309689b73df64ce21c8ed6032646281c181a.jpg", "punishTitle": "\u5728\u5f39\u5e55\u4e2d\u53d1\u5e03\u4eba\u8eab\u653b\u51fb\u8a00\u8bba", "id": 34448, "originType": 2, "blockedDays": 7, "blockedType": 0, "moralNum": 20, "uid": 11976665, "blockedForever": false, "originContentModify": "\u6211\u8981*\u8fd9\u4e2a**\u5168\u5bb6\u7684**\uff0c***\u3002", "reasonTypeName": "\u53d1\u5e03\u4eba\u8eab\u653b\u51fb\u8a00\u8bba", "uname": "\u539f\u5b50\u9082\u9005", "commentSum": 103, "punishTime": 1498253945000}