{"punishType": 2, "reasonType": 7, "face": "http://i2.hdslb.com/bfs/face/6a82dd47bf8b13e95cc6b103c2231cb75b7b4aa8.jpg", "punishTitle": "\u5728\u8bc4\u8bba\u4e2d\u53d1\u5e03\u4eba\u8eab\u653b\u51fb\u8a00\u8bba", "id": 28791, "originType": 1, "blockedDays": 3, "blockedType": 0, "moralNum": 0, "uid": 102967268, "blockedForever": false, "originContentModify": "\u8fd9\u79cd\u4eba\u8fd8\u6709***\uff1f\u4f60\u4e5f\u592a\u770b\u7684\u8d77*\u4e86\uff0c\u5b83\u80af\u5b9a\u662f******\u4e86\u968f\u4fbf\u627e\u4e2a****\u4ea4\u4e0b\u6765\u7684\u54c1\u79cd", "reasonTypeName": "\u53d1\u5e03\u4eba\u8eab\u653b\u51fb\u8a00\u8bba", "uname": "\u6d77\u76d7-\u8f9b\u5df4\u5fb7", "commentSum": 74, "punishTime": 1496212529000}