{"punishType": 2, "reasonType": 9, "face": "http://static.hdslb.com/images/member/noface.gif", "punishTitle": "\u5728\u5f39\u5e55\u4e2d\u53d1\u5e03\u5f15\u6218\u8a00\u8bba", "id": 37891, "originType": 2, "blockedDays": 7, "blockedType": 0, "moralNum": 10, "uid": 32016733, "blockedForever": false, "originContentModify": "<p>\u91cd\u5e86\u4eba***\u554a\uff0c\u597d\u9ad8\u5c1a\u7684\u76f4\u8f96\u5e02\u54e6</p><p><br></p><p>\u6279\u6ce8\uff1a\u5730\u57df\u653b\u51fb\uff0c\u4e0d\u4e88\u7f6e\u8bc4</p>", "reasonTypeName": "\u53d1\u5e03\u5f15\u6218\u8a00\u8bba", "uname": "sin\u5427\u5427\u4e3b", "commentSum": 106, "punishTime": 1499314490000}