{"punishType": 2, "reasonType": 8, "face": "http://i1.hdslb.com/bfs/face/3eb060b2d0f72f00b03fee6100e9a0e975c85778.jpg", "punishTitle": "\u5728\u5f39\u5e55\u4e2d\u53d1\u5e03\u4fb5\u72af\u4ed6\u4eba\u9690\u79c1\u4fe1\u606f", "id": 39223, "originType": 2, "blockedDays": 7, "blockedType": 0, "moralNum": 20, "uid": 95115766, "blockedForever": false, "originContentModify": "<p>\u793e\u4f1a\u738b\u7535\u8bdd\u53f7\u7801***********</p><p><br></p><p>\u6279\u6ce8\uff1a\u4e71\u53d1\u4ed6\u4eba\u624b\u673a\u4fe1\u606f\u7684\u6076\u4f5c\u5267\u5df2\u7ecf\u8fc7\u65f6\u4e86</p><p>\uff08\u8bf7\u52ff\u5728\u89c6\u9891\u73af\u5883\u5185\u53d1\u5e03\u4ed6\u4eba\u771f\u5b9e\u4fe1\u606f\uff09</p>", "reasonTypeName": "\u53d1\u5e03\u4fb5\u72af\u4ed6\u4eba\u9690\u79c1\u4fe1\u606f", "uname": "\u8bf4\u662f\u5c31\u662f\u4e86\u5427", "commentSum": 151, "punishTime": 1499672808000}