{"id": 1649, "uid": 3357874, "uname": "\u5b50sad", "face": "http://i0.hdslb.com/bfs/face/273ba58018a98dbfa967a80085e76fdbcd71c3f4.jpg", "originContentModify": "\u770b\u7740\u8fd9\u7247\u5b50\u4f60\u5c45\u7136\u8fd8\u80fd\u4e0d\u8981\u4f60***\u7684\u7684\u6d17\u4f60\u89c1\u6b7b\u4e0d\u6551\u653b\u51fb\u7acb\u6b62\u7684**\uff1f\u770b\u4ed6\u4eec\u4e00\u4e2a\u4e2a\u6b7b\u4f60\u6ca1\u6709\u534a\u70b9\u6124\u6168\uff1f\uff1f\u679c\u7c89\u679c\u7136\u90fd\u662f*****\u7684\u975e\u4eba\u7269\u4ef6\uff0c*****\u679c\u7136\u90fd\u662f******\uff0c\u7adf\u6ca1\u6709\u534a\u70b9\u4eba\u5fc3\uff01", "originType": 1, "reasonType": 9, "punishTime": 1488513309000, "punishType": 2, "moralNum": 0, "blockedDays": 3, "blockedForever": false, "commentSum": 265, "punishTitle": "\u5728\u8bc4\u8bba\u4e2d\u53d1\u5e03\u5f15\u6218\u8a00\u8bba", "reasonTypeName": "\u53d1\u5e03\u5f15\u6218\u8a00\u8bba"}