{"id": 22618, "uid": 14908757, "uname": "\u6211\u5361\u5e03\u62c9\u5de8\u4eba\u4e00\u94f2\u5b50", "face": "http://i1.hdslb.com/bfs/face/a8db52736a0c02631af45d5c34de89c49538bd27.jpg", "originContentModify": "\u5389\u5bb3 \u81ea\u5df1\u7d20\u8d28\u4f4e\u8fd8\u80fd\u628a\u9505\u7529\u7ed9\u522b\u4eba \u4e2d\u56fd\u4eba\u5957\u8def\u5012\u662f\u8001\u6bcd\u732a\u5e26\u80f8\u7f69\u4e00\u5957\u53c8\u4e00\u5957", "originType": 1, "reasonType": 9, "punishTime": 1494583327000, "punishType": 2, "moralNum": 0, "blockedDays": 3, "blockedForever": false, "commentSum": 364, "punishTitle": "\u5728\u8bc4\u8bba\u4e2d\u53d1\u5e03\u5f15\u6218\u8a00\u8bba", "reasonTypeName": "\u53d1\u5e03\u5f15\u6218\u8a00\u8bba"}