{"id": 25797, "uid": 5356122, "uname": "\u4e2d\u4e8c\u7684\u6e21\u9e26", "face": "http://i0.hdslb.com/bfs/face/703a4075b7bec230bc7336400f814dba2379716a.jpg", "originContentModify": "**\u7089\u5229**\u7121\u9650**\u3057 &nbsp;***** ****", "originType": 2, "reasonType": 13, "punishTime": 1495424030000, "punishType": 2, "moralNum": 20, "blockedDays": 3, "blockedForever": false, "commentSum": 48, "punishTitle": "\u5728\u5f39\u5e55\u4e2d\u53d1\u5e03\u8272\u60c5\u4fe1\u606f", "reasonTypeName": "\u53d1\u5e03\u8272\u60c5\u4fe1\u606f"}