{"id": 30348, "uid": 18983359, "uname": "\u4e5f\u8bb8\u662f\u6700\u5f3a\u7684\u7537\u4eba", "face": "http://i2.hdslb.com/bfs/face/d2013af769929155c5065592e6589bb4170cf13a.jpg", "originContentModify": "\u73a9\u817e\u8baf\u6e38\u620f\u7684\u90fd\u662fsb", "originType": 1, "reasonType": 9, "punishTime": 1496798708000, "punishType": 2, "moralNum": 0, "blockedDays": 3, "blockedType": 0, "blockedForever": false, "commentSum": 226, "punishTitle": "\u5728\u8bc4\u8bba\u4e2d\u53d1\u5e03\u5f15\u6218\u8a00\u8bba", "reasonTypeName": "\u53d1\u5e03\u5f15\u6218\u8a00\u8bba"}