{"id": 33670, "uid": 18438087, "uname": "\u6050\u6016\u7164\u5316\u5de5", "face": "http://i0.hdslb.com/bfs/face/186507577d4682928f58dd04fbc10696512283ee.jpg", "originContentModify": "\u6240\u4ee5\u4f60\u62a5\u4e0b***\u5730\u5740  \u6211\u60f3*****\u7684**** \u6ee1\u8db3***", "originType": 1, "reasonType": 7, "punishTime": 1497923663000, "punishType": 2, "moralNum": 0, "blockedDays": 7, "blockedType": 0, "blockedForever": false, "commentSum": 73, "punishTitle": "\u5728\u8bc4\u8bba\u4e2d\u53d1\u5e03\u4eba\u8eab\u653b\u51fb\u8a00\u8bba", "reasonTypeName": "\u53d1\u5e03\u4eba\u8eab\u653b\u51fb\u8a00\u8bba"}