{"originContentModify": "<p>\u300e\u4e00\u4e8c\u4e09\u7fa4\u5df2\u6ee1.\u8bf7\u52a0\u6b64\u7fa4\uff1a***********.\u671b\u7406\u89e3\u300f</p><p><br></p><p>\u6279\u6ce8\uff1a\u4e0d\u7406\u89e3\u3010\u53f3\u952e-\u4e3e\u62a5-\u5783\u573e\u5e7f\u544a\u4fe1\u606f\u3011</p><p>\uff08\u8bf7\u52ff\u5728\u89c6\u9891\u5185\u53d1\u5e03\u5fae\u4fe1qq\u7b49\u5e7f\u544a\u4fe1\u606f\uff09</p>", "uid": 86244797, "blockedForever": false, "originType": 2, "punishTime": 1501125513000, "reasonTypeName": "\u53d1\u5e03\u5783\u573e\u5e7f\u544a\u4fe1\u606f", "moralNum": 10, "id": 47837, "punishTitle": "\u5728\u5f39\u5e55\u4e2d\u53d1\u5e03\u5783\u573e\u5e7f\u544a\u4fe1\u606f", "blockedDays": 15, "reasonType": 6, "uname": "", "commentSum": 38, "blockedType": 0, "punishType": 2}