{"blockedDays": 7, "punishTime": 1502626541000, "id": 53704, "blockedForever": false, "uid": 24382846, "uname": "", "moralNum": 0, "originContentModify": "\u867d\u7136\u6211\u4e0d\u61c2\u8df3\u821e\uff0c\u4f46\u662f\u6211\u53ea\u60f3\u8bf4\u4e00\u53e5\u6211\u81ea\u5df1\u8ba4\u4e3a\u7684\u4e00\u53e5\u8bdd\uff0c\u8df3\u7684\u8ddf\u5c4e\u4e00\u6837\uff0c\u867d\u7136\u6211\u8df3\u4e0d\u51fa\u6765\uff0c\u56e0\u4e3a\u6211\u662f\u753b\u753b\u7684\u554a233333333333333", "blockedType": 1, "punishType": 2, "originType": 1, "reasonTypeName": "\u53d1\u5e03\u5f15\u6218\u8a00\u8bba", "punishTitle": "\u5728\u8bc4\u8bba\u4e2d\u53d1\u5e03\u5f15\u6218\u8a00\u8bba", "commentSum": 232, "reasonType": 9}