{"id": 60149, "punishTitle": "\u5728\u5f39\u5e55\u4e2d\u53d1\u5e03\u5f15\u6218\u8a00\u8bba", "blockedForever": false, "punishTime": 1504149049000, "uname": "", "blockedDays": 7, "originContentModify": "<p>**\u4eec\u53ef\u4ee5\u548c\u888b\u9f20\u4eec\u7ed3\u5a5a\uff0c\u7136\u540e\u7ed9\u4ed6\u4eec\u53d1\u62a4\u7167\u5440~</p><p><br></p><p>\u6279\u6ce8\uff1a\u7b7e\u8bc1\u600e\u4e48\u529e\uff1f</p><p>\uff08\u8bf7\u52ff\u5728\u89c6\u9891\u5185\u53d1\u5e03\u8bbd\u523a\u5f15\u6218\u5f39\u5e55\uff0c\u53d1\u73b0\u76f8\u5173\u5185\u5bb9\u8bf7\u6309\u7167\u5f15\u6218\u4e3e\u62a5\uff09</p>", "commentSum": 92, "punishType": 2, "uid": 559259, "blockedType": 0, "moralNum": 10, "reasonTypeName": "\u53d1\u5e03\u5f15\u6218\u8a00\u8bba", "originType": 2, "reasonType": 9}