{"reasonTypeName": "\u53d1\u5e03\u5783\u573e\u5e7f\u544a\u4fe1\u606f", "blockedDays": 0, "blockedType": 0, "originContentModify": "<p>\u8fd8\u6709\u6ca1\u6709\u50cf****\u4e00\u6837\u4e0d\u7528\u6c2a\u91d1\u7eaf\u9760\u6280\u672f\u7684\u6e38\u620f\u7ed9\u6211\u6765\u4e00\u6253\uff01</p><p><br></p><p>\u6279\u6ce8\uff1a\u5df2\u7ecf\u5c01\u7981\u4e86\u4e00\u6253\u540c\u6837\u5185\u5bb9\u7684\u5c0f\u5e7f\u544a\u4e86</p><p>\uff08\u8bf7\u52ff\u4f7f\u7528\u5f39\u5e55\u53d1\u5e03\u5783\u573e\u5e7f\u544a\u5185\u5bb9\uff09</p>", "punishTime": 1500360040000, "uid": 82359568, "commentSum": 102, "id": 42674, "punishType": 2, "moralNum": 10, "blockedForever": true, "uname": "nzhzhl9555", "face": "http://static.hdslb.com/images/member/noface.gif", "reasonType": 6, "originType": 2, "punishTitle": "\u5728\u5f39\u5e55\u4e2d\u53d1\u5e03\u5783\u573e\u5e7f\u544a\u4fe1\u606f"}