{"blockedDays": 7, "punishTime": 1502176470000, "id": 51767, "blockedForever": false, "uid": 19248495, "uname": "", "moralNum": 20, "originContentModify": "<p>\u2193\u51f6\u624b\u2193</p><p><br></p><p>\u6279\u6ce8\uff1a\u662f\u662f\u662f\uff0c\u5267\u900f\u5904\u7f5a7\u5929</p><p>\uff08\u8bf7\u52ff\u5728\u89c6\u9891\u5185\u53d1\u5e03\u5267\u900f\u5185\u5bb9\uff09</p>", "blockedType": 0, "punishType": 2, "originType": 2, "reasonTypeName": "\u53d1\u5e03\u5267\u900f\u4fe1\u606f", "punishTitle": "\u5728\u5f39\u5e55\u4e2d\u53d1\u5e03\u5267\u900f\u4fe1\u606f", "commentSum": 88, "reasonType": 10}