{"id": 60053, "punishTitle": "\u5728\u5f39\u5e55\u4e2d\u6076\u610f\u5237\u5c4f", "blockedForever": false, "punishTime": 1504090985000, "uname": "", "blockedDays": 7, "originContentModify": "<p>\u5927\u5bb6\uff0c\u8bb0\u4f4f\u6211\u7684\u540d\u5b57\uff0c**</p><p><br></p><p>\u6279\u6ce8\uff1a\u5e78\u4f1a\u5e78\u4f1a\uff0c\u5728\u4e0b\u53f6*\u8fb0</p><p>\uff08\u8bf7\u52ff\u5728\u89c6\u9891\u5185\u53d1\u5e03\u5237\u5c4f\u4fe1\u606f\uff0c\u5f71\u54cd\u4ed6\u4eba\u89c2\u770b\u4f53\u9a8c\uff09</p>", "commentSum": 129, "punishType": 2, "uid": 4585222, "blockedType": 0, "moralNum": 2, "reasonTypeName": "\u6076\u610f\u5237\u5c4f", "originType": 2, "reasonType": 20}