{"punishType": 2, "reasonType": 6, "face": "http://static.hdslb.com/images/member/noface.gif", "punishTitle": "\u5728\u5f39\u5e55\u4e2d\u53d1\u5e03\u5783\u573e\u5e7f\u544a\u4fe1\u606f", "id": 26563, "originType": 2, "blockedDays": 7, "blockedType": 0, "moralNum": 10, "uid": 81694130, "blockedForever": false, "originContentModify": "\u53d1\u8f66\u4e86*****\u70b9C0M\u53eb\u6211\u96f7\u950b\u4e0d\u8c22\u901f\u8bb0**", "reasonTypeName": "\u53d1\u5e03\u5783\u573e\u5e7f\u544a\u4fe1\u606f", "uname": "rhjnbp3771", "commentSum": 80, "punishTime": 1495779199000}