{"uname": "", "id": 58586, "blockedType": 0, "blockedDays": 7, "originContentModify": "<p>\u6211\uff0c\u7530**\uff0c8.26\uff0c\u5408\u5f71\u7559\u5ff5&nbsp;</p><p>&nbsp;</p><p>\u6279\u6ce8\uff1a\u201c\u4f60\u7684\u540d\u5b57\uff1f\u201d&nbsp;</p><p>&nbsp; &nbsp; &nbsp; &nbsp; &nbsp; &nbsp;\u201c\u7530**\u201d</p><p>&nbsp; &nbsp; &nbsp; &nbsp; &nbsp; &nbsp;\u201c\u6848\u7531\u5237\u5c4f\uff0c\u5904\u7f5a\u65f6\u957f7\u5929\uff0c\u7f16\u53f758586\uff0c\u670d\u5211\u671f\u95f4\u8bf7\u52a1\u5fc5\u597d\u597d\u53cd\u7701\u201d</p><p><br></p>", "punishType": 2, "punishTime": 1503744548000, "reasonType": 20, "moralNum": 0, "commentSum": 53, "uid": 33544382, "blockedForever": false, "reasonTypeName": "\u6076\u610f\u5237\u5c4f", "originType": 2, "punishTitle": "\u5728\u5f39\u5e55\u4e2d\u6076\u610f\u5237\u5c4f"}